dbnd_mlflow/__init__.py
dbnd_mlflow/databand_store.py
dbnd_mlflow/mlflow_config.py
dbnd_mlflow/mlflow_with_dbnd_tracking.py
dbnd_mlflow/tracking_store.py
dbnd_mlflow/url_utils.py
dbnd_mlflow/testing/__init__.py
dbnd_mlflow/testing/mlflow_example.py
dbnd_mlflow-1.0.30.1.dist-info/LICENSE
dbnd_mlflow-1.0.30.1.dist-info/METADATA
dbnd_mlflow-1.0.30.1.dist-info/WHEEL
dbnd_mlflow-1.0.30.1.dist-info/entry_points.txt
dbnd_mlflow-1.0.30.1.dist-info/top_level.txt
dbnd_mlflow-1.0.30.1.dist-info/RECORD
